[{"title":"Captain America: The First Avenger","desc":"March 1942-May 1945\nApril 2011 (Present Day)"},{"title":"Marvel One-Shot: Agent Carter","desc":"March 1946"},{"title":"Agent Carter","desc":"April-May 1946 / Season 1\nJuly 1947 / Season 2"},{"title":"Captain Marvel","desc":"June 1995"},{"title":"Iron Man","desc":"January-May 2008"},{"title":"Iron Man 2","desc":"May-June 2011"},{"title":"Marvel One-Shot: A Funny Thing Happened on the Way to Thor's Hammer","desc":"June 2011"},{"title":"Thor","desc":"June 2011"},{"title":"The Incredible Hulk","desc":"April-July 2011"},{"title":"Marvel One-Shot: The Consultant","desc":"July 2011"},{"title":"The Avengers","desc":"May 2012"},{"title":"Marvel One-Shot: Item 47","desc":"May 2012"},{"title":"Iron Man Three","desc":"December 2012"},{"title":"Marvel One-Shot: All Hail the King","desc":"2013"},{"title":"Agents of S.H.I.E.L.D.","desc":"September-November 2013 / Season 1 Ep. 1-7"},{"title":"Thor: The Dark World","desc":"November 2013"},{"title":"Agents of S.H.I.E.L.D.","desc":"November 2013-January 2014 / Season 1 Ep. 8-16"},{"title":"Captain America: The Winter Soldier","desc":"January 2014"},{"title":"Agents of S.H.I.E.L.D.","desc":"January 2014 / Season 1 Ep. 17-22\nApril 2014 / Season 2 Ep. 1-2"},{"title":"Guardians of the Galaxy","desc":"2014"},{"title":"I Am Groot","desc":"2014 / Season 1 Ep. 1"},{"title":"Agents of S.H.I.E.L.D.","desc":"2014 / Season 2 Ep. 3"},{"title":"Guardians of the Galaxy Vol. 2","desc":"2014"},{"title":"I Am Groot","desc":"2014 / Season 1 Ep. 2-5"},{"title":"Daredevil","desc":"2014 / Season 1"},{"title":"Jessica Jones","desc":"January-March 2015 / Season 1"},{"title":"Agents of S.H.I.E.L.D.","desc":"March-April 2015 / Season 2 Ep. 4-19"},{"title":"Avengers: Age of Ultron","desc":"April-May 2015"},{"title":"Agents of S.H.I.E.L.D.","desc":"April 2015 / Season 2 Ep. 20-22"},{"title":"WHIH News Front","desc":"July 2015 / Season 1"},{"title":"Daredevil","desc":"July 2015 / Season 2 Ep. 1-6"},{"title":"Ant-Man","desc":"September-October 2015"},{"title":"Agents of S.H.I.E.L.D.","desc":"October-November 2015 / Season 3 Ep. 1-8"},{"title":"Daredevil","desc":"November 2015 / Season 2 Ep. 7-13"},{"title":"Luke Cage","desc":"November-December 2015 / Season 1"},{"title":"Agents of S.H.I.E.L.D.","desc":"December 2015-April 2016 / Season 3 Ep. 9-19"},{"title":"WHIH News Front","desc":"March 2016 / Season 2"},{"title":"Captain America: Civil War","desc":"March-April 2016"},{"title":"Agents of S.H.I.E.L.D.","desc":"April 2016 / Season 3 Ep. 20-22"},{"title":"Black Widow","desc":"April 2016"},{"title":"Black Panther","desc":"April 2016"},{"title":"Iron Fist","desc":"June-July 2016 / Season 1"},{"title":"Inhumans","desc":"2016 / Season 1"},{"title":"Spider-Man: Homecoming","desc":"October 2016"},{"title":"The Defenders","desc":"November 2016 / Season 1"},{"title":"The Punisher","desc":"November-December 2016 / Season 1"},{"title":"Doctor Strange","desc":"February 2016-February 2017"},{"title":"Cloak & Dagger","desc":"February-March 2017 / Season 1"},{"title":"Agents of S.H.I.E.L.D.","desc":"April 2017 / Season 4 Ep. 1-8"},{"title":"Agents of S.H.I.E.L.D.: Slingshot","desc":"April 2017"},{"title":"Agents of S.H.I.E.L.D.","desc":"April 2017 / Season 4 Ep. 9-12"},{"title":"Jessica Jones","desc":"April-May 2017 / Season 2"},{"title":"Agents of S.H.I.E.L.D.","desc":"May 2017 / Season 4 Ep. 13-22"},{"title":"Luke Cage","desc":"August-September 2017 / Season 2"},{"title":"Daredevil","desc":"October 2017 / Season 3"},{"title":"Cloak & Dagger","desc":"October-November 2017 / Season 2"},{"title":"Agents of S.H.I.E.L.D.","desc":"Time Travel (2091) then return to Present Day / Season 5 Ep. 1-10"},{"title":"Thor: Ragnarok","desc":"November 2017"},{"title":"Agents of S.H.I.E.L.D.","desc":"December 2017 / Season 5 Ep. 11-13"},{"title":"Runaways","desc":"December 2017 / Season 1"},{"title":"Iron Fist","desc":"January 2018 / Season 2 Ep. 1-7"},{"title":"Runaways","desc":"January 2018 / Season 2\nJanuary 2018 / Season 3 Ep. 1-4"},{"title":"Iron Fist","desc":"February 2018 / Season 2 Ep. 8-10"},{"title":"Jessica Jones","desc":"2018 / Season 3"},{"title":"The Punisher","desc":"April 2018 / Season 2 Ep. 1-5"},{"title":"Ant-Man and the Wasp","desc":"April-May 2018"},{"title":"The Punisher","desc":"May 2018 / Season 2 Ep. 6-13"},{"title":"Agents of S.H.I.E.L.D.","desc":"May 2018 / Season 5 Ep. 14-22"},{"title":"Avengers: Infinity War","desc":"May 2018"},{"title":"Runaways","desc":"August 2018 / Season 3 Ep. 5-10"},{"title":"Agents of S.H.I.E.L.D.","desc":"January 2019 / Season 6\nTime Travel (1931-1983) then return to January 2019-2020 / Season 7"},{"title":"Helstrom","desc":"November-December 2020 / Season 1"},{"title":"Avengers: Endgame","desc":"October 2023"},{"title":"Loki","desc":"Loki from Avengers: Endgame Time Heist escape to TVA/Void/End of Time / Season 1"},{"title":"What If...?","desc":"Take place after Loki Season 1 started the Multiverse / Season 1"},{"title":"Eternals","desc":"October 2023"},{"title":"WandaVision","desc":"November 2023 / Season 1"},{"title":"Shang-Chi and the Legend of the Ten Rings","desc":"March-April 2024"},{"title":"The Falcon and the Winter Soldier","desc":"April-May 2024 / Season 1"},{"title":"Thor: Love and Thunder","desc":"May 2024"},{"title":"Moon Knight","desc":"June 2024 / Season 1"},{"title":"Peter's To-Do List","desc":"June 2024"},{"title":"Spider-Man: Far from Home","desc":"June-July 2024"},{"title":"Spider-Man: No Way Home","desc":"July-December 2024"},{"title":"Doctor Strange in the Multiverse of Madness","desc":"November-December 2024"},{"title":"Hawkeye","desc":"December 2024 / Season 1"},{"title":"Black Panther: Wakanda Forever","desc":"May 2025"},{"title":"She-Hulk: Attorney at Law","desc":"June-August 2025 / Season 1"},{"title":"Ms. Marvel","desc":"September-October 2025 / Season 1"},{"title":"Secret Invasion","desc":"October-November 2025 / Season 1"},{"title":"Werewolf by Night","desc":"2025"},{"title":"The Guardians of the Galaxy Holiday Special","desc":"December 2025"},{"title":"Guardians of the Galaxy Vol. 3","desc":"2026"},{"title":"Ant-Man and the Wasp: Quantumania","desc":"July-August 2026"}]
